emailsherlock.py
emailsherlock/__init__.py
emailsherlock/cli.py
emailsherlock/core.py
emailsherlock-1.0.dist-info/LICENSE
emailsherlock-1.0.dist-info/METADATA
emailsherlock-1.0.dist-info/WHEEL
emailsherlock-1.0.dist-info/entry_points.txt
emailsherlock-1.0.dist-info/top_level.txt
emailsherlock-1.0.dist-info/RECORD
