Metadata-Version: 2.1
Name: emailsherlock
Version: 1.0
Summary: A powerful email validation tool using DNS and SMTP checks
Home-page: https://github.com/asimd/emailsherlock
Author: Asim Delalic
Author-email: delalic.asim@gmail.com
Classifier: Development Status :: 3 - Alpha
Classifier: Intended Audience :: Developers
Classifier: License :: OSI Approved :: MIT License
Classifier: Operating System :: OS Independent
Classifier: Programming Language :: Python :: 3
Classifier: Programming Language :: Python :: 3.7
Classifier: Programming Language :: Python :: 3.8
Classifier: Programming Language :: Python :: 3.9
Classifier: Programming Language :: Python :: 3.10
Requires-Python: >=3.7
License-File: LICENSE
Requires-Dist: dnspython>=2.1.0
